red_connector_xnat/__init__.py
red_connector_xnat/cli_modes.py
red_connector_xnat/helpers.py
red_connector_xnat/main.py
red_connector_xnat/schemas.py
red_connector_xnat/send_receive_file.py
red_connector_xnat/version.py
red_connector_xnat-1.0.dist-info/entry_points.txt
red_connector_xnat-1.0.dist-info/LICENSE
red_connector_xnat-1.0.dist-info/WHEEL
red_connector_xnat-1.0.dist-info/METADATA
red_connector_xnat-1.0.dist-info/RECORD
