Metadata-Version: 2.1
Name: red-connector-xnat
Version: 1.0
Summary: RED Connector XNAT is part of the Curious Containers project.
Home-page: https://www.curious-containers.cc/
License: AGPL-3.0
Author: Christoph Jansen
Author-email: Christoph.Jansen@htw-berlin.de
Requires-Python: >=3.4,<4.0
Classifier: License :: OSI Approved :: GNU Affero General Public License v3
Classifier: Programming Language :: Python :: 3
Classifier: Programming Language :: Python :: 3.4
Classifier: Programming Language :: Python :: 3.5
Classifier: Programming Language :: Python :: 3.6
Classifier: Programming Language :: Python :: 3.7
Requires-Dist: jsonschema (>=3.0,<4.0)
Requires-Dist: requests (>=2.18,<3.0)
Project-URL: Repository, https://github.com/curious-containers/red-connector-xnat
